lab_1_wilcox/__init__.py
lab_1_wilcox/main.py
wilcox_lab_1-1.1.5.data/scripts/show-current-time.py
wilcox_lab_1-1.1.5.dist-info/LICENSE
wilcox_lab_1-1.1.5.dist-info/METADATA
wilcox_lab_1-1.1.5.dist-info/WHEEL
wilcox_lab_1-1.1.5.dist-info/top_level.txt
wilcox_lab_1-1.1.5.dist-info/RECORD
