Metadata-Version: 2.1
Name: wilcox-lab-1
Version: 1.1.5
Author: Gregory Wilcox
Author-email: wilcox12@canisius.edu
License: Apache License Version 2.0
License-File: LICENSE
Requires-Dist: Flask
Requires-Dist: Dash
Requires-Dist: dash-bootstrap-components
